{
  "dependencies": [
    "464D0C17601E8A2B"
  ],
  "tasks": {},
  "rewards": {},
  "display": {
    "subtitle": {
      "text": ""
    },
    "description": [
      "<task task=\"5C777F84736455DA\" quest=\"653487501398DECA\"/>",
      "<hr/>",
      "<hr/>",
      "<reward reward=\"743B3A79F4825FDD\" quest=\"653487501398DECA\"/>"
    ],
    "groups": {
      "§aChapter 3§r: §dCreative": {
        "position": [
          -64,
          16
        ]
      }
    },
    "icon": {
      "item": {
        "id": "minecraft:air",
        "count": 0
      },
      "type": "heracles:item"
    },
    "icon_background": "heracles:textures/gui/quest_backgrounds/default.png",
    "title": {
      "translate": "i18n.quest.chapter3.jetpack"
    }
  },
  "settings": {
    "showDependencyArrow": true,
    "repeatable": false,
    "autoClaimRewards": false,
    "individual_progress": false,
    "hidden": "LOCKED",
    "unlockNotification": false
  }
}